pydicti/__init__.py
pydicti/py.typed
pydicti/pydicti.py
pydicti/pydicti.pyi
pydicti-1.2.1.dist-info/LICENSE
pydicti-1.2.1.dist-info/METADATA
pydicti-1.2.1.dist-info/WHEEL
pydicti-1.2.1.dist-info/top_level.txt
pydicti-1.2.1.dist-info/zip-safe
pydicti-1.2.1.dist-info/RECORD
