Metadata-Version: 2.1
Name: pydicti
Version: 1.2.1
Summary: Case insensitive derivable dictionary
Home-page: https://github.com/coldfix/pydicti
Author: Thomas Gläßle
Author-email: t_glaessle@gmx.de
License: WTFPL
Platform: UNKNOWN
Classifier: Development Status :: 5 - Production/Stable
Classifier: Intended Audience :: Developers
Classifier: Operating System :: OS Independent
Classifier: Programming Language :: Python
Classifier: Programming Language :: Python :: 2.7
Classifier: Programming Language :: Python :: 3
Classifier: Topic :: Software Development
Requires-Python: >=2.7
License-File: LICENSE
